pysirix/__init__.py
pysirix/async_client.py
pysirix/auth.py
pysirix/constants.py
pysirix/database.py
pysirix/errors.py
pysirix/info.py
pysirix/json_store.py
pysirix/resource.py
pysirix/sirix.py
pysirix/sync_client.py
pysirix/types.py
pysirix/shell/__init__.py
pysirix/shell/__main__.py
pysirix/shell/sirixsh.py
pysirix-0.5.3.dist-info/LICENSE
pysirix-0.5.3.dist-info/METADATA
pysirix-0.5.3.dist-info/WHEEL
pysirix-0.5.3.dist-info/entry_points.txt
pysirix-0.5.3.dist-info/top_level.txt
pysirix-0.5.3.dist-info/RECORD
