Metadata-Version: 2.1
Name: pysirix
Version: 0.5.3
Summary: The SirixDB Python SDK
Home-page: https://github.com/sirixdb/sirix-python-client
Author: Moshe Uminer
Author-email: mosheduminer@gmail.com
License: UNKNOWN
Platform: UNKNOWN
Classifier: Programming Language :: Python :: 3
Classifier: License :: OSI Approved :: Apache Software License
Classifier: Operating System :: OS Independent
Requires-Python: >=3.7
License-File: LICENSE
Requires-Dist: httpx (~=0.21.0)
